opensearchorm/__init__.py
opensearchorm/aggs.py
opensearchorm/model.py
opensearchorm/query.py
opensearchorm/session.py
opensearchorm/utils.py
opensearch_orm-0.2.1.dist-info/LICENSE
opensearch_orm-0.2.1.dist-info/METADATA
opensearch_orm-0.2.1.dist-info/WHEEL
opensearch_orm-0.2.1.dist-info/RECORD
