Metadata-Version: 2.1
Name: opensearch-orm
Version: 0.2.1
Summary: 
Author: yim7
Author-email: yimchiu7@gmail.com
Requires-Python: >=3.7,<4.0
Classifier: Programming Language :: Python :: 3
Classifier: Programming Language :: Python :: 3.7
Classifier: Programming Language :: Python :: 3.8
Classifier: Programming Language :: Python :: 3.9
Classifier: Programming Language :: Python :: 3.10
Classifier: Programming Language :: Python :: 3.11
Requires-Dist: opensearch-py (>=1.0.0,<2.0.0)
Requires-Dist: pydantic (>=1.6.0,<2.0.0)
Requires-Dist: pytz (>=2022.2.1,<2023.0.0)
